[{"uid": "6401071393", "mid": "4238544677740605", "user_name": "企税银", "text": "听说杀害空姐的滴滴司机被抓住了，这个是不是真的？#空姐滴滴打车遭司机杀害# 2杭州·良渚 L十八点一的烦恼的秒拍视频", "parent": null, "t": "1526031240"}, {"uid": "6401071393", "mid": "4238546204226546", "user_name": "企税银", "text": "我也不知是不是，问问", "parent": "4238544677740605", "t": "1526031600"}, {"uid": "5896425468", "mid": "4238550527906125", "user_name": "南陈依子", "text": "假的", "parent": "4238546204226546", "t": "1526032620"}, {"uid": "6401071393", "mid": "4238544933773157", "user_name": "企税银", "text": "这个是真的吗？", "parent": "4238544677740605", "t": "1526031300"}, {"uid": "6355786531", "mid": "4239530401470718", "user_name": "特仑苏哇", "text": "这些人有意思吗这样子   人家都公布凶手自杀了", "parent": "4238544677740605", "t": "1526266260"}, {"uid": "5516789038", "mid": "4239598882122422", "user_name": "吃糖日子就不会苦了", "text": "已经确实司机死亡了", "parent": "4238544677740605", "t": "1526282580"}, {"uid": "6187157637", "mid": "4239354362445966", "user_name": "坚强的棒棒糖_987", "text": "拿测慌仪测一下就真相大白了。", "parent": "4238544677740605", "t": "1526224260"}, {"uid": "3802058233", "mid": "4238546955021744", "user_name": "爱抓耗子的狗", "text": "都说跳河了 现在在打捞", "parent": "4238544677740605", "t": "1526031780"}, {"uid": "6186678634", "mid": "4238546522777649", "user_name": "Cc国际医疗整形官方微博", "text": "朋友，以这个蹭热度，合适吗？", "parent": "4238544677740605", "t": "1526031660"}, {"uid": "6330087441", "mid": "4238545394560574", "user_name": "内心的牵挂", "text": "脸都没看到，你想火？怕没那么容易哦", "parent": "4238544677740605", "t": "1526031420"}, {"uid": "6383663730", "mid": "4239196471912424", "user_name": "野驴大哥的傻猴子", "text": "又是抖音  你他妈是脑残吗", "parent": "4238544677740605", "t": "1526186640"}]